pyspotriver/data/__init__.py
pyspotriver/data/airline-passengers.csv
pyspotriver/data/airline_passengers.py
pyspotriver/data/base.py
pyspotriver/data/synth/__init__.py
pyspotriver/data/synth/sea.py
pyspotriver/fun/hyperriver.py
pyspotriver-0.0.1.dist-info/LICENSE
pyspotriver-0.0.1.dist-info/METADATA
pyspotriver-0.0.1.dist-info/WHEEL
pyspotriver-0.0.1.dist-info/top_level.txt
pyspotriver-0.0.1.dist-info/RECORD
