Metadata-Version: 2.1
Name: pyspotriver
Version: 0.0.1
Summary: pyspotriver - Python Sequential Parameter Optimization Interface to River
Author-email: "T. Bartz-Beielstein" <tbb@bartzundbartz.de>
Project-URL: Homepage, https://www.spotseven.de
Classifier: Programming Language :: Python :: 3.10
Classifier: Programming Language :: Python :: 3.11
Classifier: Operating System :: OS Independent
Requires-Python: >=3.10
License-File: LICENSE
Requires-Dist: mkdocstrings-python
